Workbook

Sheet Weekly Info
A1: week_start
A2: week_end
A3: number_of_paid_events
A4: total_guests

Sheet Event_PnL
A1: event_date
A2: event_name
A3: event_type
A4: guest_count
A6: space_fee
A7: food_revenue
A8: beverage_revenue
A9: admin_fee
A10: sales_tax
A11: gross_revenue
A12: net_revenue | B12: =B11-B10 -> 0
A14: additional_labor_cost
A15: in_house_hourly_labor_cost
A16: outsourced_labor_cost | B16: 0
A17: total_labor_cost | B17: =SUM(B14:B16) -> 0
A18: approx_food_cost
A19: approx_beverage_cost | B19: =20% * B8 -> 0
A20: rentals | B20: 0
A21: approx_operating_cost | B21: =SUM(B14:B20) -> 0
A23: operating_profit | B23: =B12-B21 -> 0
A24: margin_pct | B24: =B23/B12 -> #DIV/0!
A26: revenue_per_guest | B26: =B12/B4 -> #DIV/0!
A27: food_and_bev_cost_per_guest | B27: =(B18 + B19) / B4 -> #DIV/0!
A28: labor_cost_per_guest | B28: =SUM(B14:B16) / B4 -> #DIV/0!
A29: profit_per_guest | B29: =B26-B27-B28 -> #DIV/0!

Sheet Weekly Summary
A1: metric | B1: value
A2: Gross Revenue | B2: =SUM(Event_PnL!B11:Z11) -> 0
A3: Net Revenue | B3: =B2-B8 -> 0
A4: Total Food and Bev Cost | B4: =SUM((Event_PnL!B18:Z18):(Event_PnL!B19:Z19)) -> 0
A5: Total Food and Bev Cost % | B5: =B4/B3 -> #DIV/0!
A6: Total Labor Cost | B6: =SUM(Labor!D2) -> 0
A7: Total Labor Cost % | B7: =B6/B3 -> #DIV/0!
A8: Total Sales Tax | B8: =SUM(Event_PnL!B10:Z10) -> 0
A9: Opertaing Cost | B9: =SUM(B4,B6) -> 0
A10: Total Operating Profit | B10: =SUM(Event_PnL!B23:Z23) -> 0
A11: Operating Cost % | B11: =B9/B3 -> #DIV/0!
A12: Profit Margin % | B12: =(B10/B3) -> #DIV/0!

Sheet Labor
A1: event_date | B1: event_name | C1: event_labor_cost | D1: weekly_labor_cost

Sheet Invoices
A1: invoice_date | B1: vendor | C1: invoice_number | D1: category | E1: cost | F1: notes | G1: total_cost
G2: =SUM(E2:E10) -> 0

Sheet Charts
