Workbook

Sheet Weekly Info
A1: week_start
A2: week_end
A3: number_of_paid_events
A4: total_guests

Sheet Event_PnL
A1: event_date | B1: 03-07-2026 | C1: 03-05-2026 | D1: 03-07-2026
A2: event_name | B2: One for Democracy | C2: Marble Collective | D2: Emma & Jake
A3: event_type | B3: Panel | C3: Cocktail Reception / Crudite & Mezze | D3: Engagement Party/ canapes, small plates, station
A4: guest_count | B4: 50 | C4: 65 | D4: 125
A6: space_fee | B6: 0 | C6: 3375 | D6: 5000
A7: food_revenue | B7: 14990 | C7: 3770 | D7: 18750
A8: beverage_revenue | B8: 2700 | C8: 1300 | D8: 18750
A9: admin_fee | B9: 4068.7 | C9: 2018.25 | D9: 9775
A10: sales_tax | B10: 1931.08 | C10: 957.9 | D10: 0
A11: gross_revenue | B11: 23689.78 | C11: 11751.15 | D11: 52275
A12: net_revenue | B12: =B11-B10 | C12: =C11-C10 | D12: =D11-D10
A14: additional_labor_cost | B14: 0 | C14: 330 | D14: 0
A15: in_house_hourly_labor_cost | B15: 2874.75 | C15: 2873.2 | D15: 4370.08
A16: outsourced_labor_cost | B16: 0 | C16: 0 | D16: 0
A17: total_labor_cost | B17: =SUM(B14:B16) | C17: =SUM(C14:C16) | D17: =SUM(D14:D16)
A18: approx_food_cost | B18: 1548.5 | C18: 637.06 | D18: 3008.56
A19: approx_beverage_cost | B19: =20% * B8 | C19: =20% * C8 | D19: =20% * D8
A20: rentals | B20: 0 | C20: 0 | D20: 0
A21: approx_operating_cost | B21: =SUM(B14:B20) | C21: =SUM(C14:C20) | D21: =SUM(D14:D20)
A23: operating_profit | B23: =B12-B21 | C23: =C12-C21 | D23: =D12-D21
A24: margin_pct | B24: =B23/B12 | C24: =C23/C12 | D24: =D23/D12
A26: revenue_per_guest | B26: =B12/B4 | C26: =C12/C4 | D26: =D12/D4
A27: food_and_bev_cost_per_guest | B27: =(B18 + B19) / B4 | C27: =(C18 + C19) / C4 | D27: =(D18 + D19) / D4
A28: labor_cost_per_guest | B28: =SUM(B14:B16) / B4 | C28: =SUM(C14:C16) / C4 | D28: =SUM(D14:D16) / D4
A29: profit_per_guest | B29: =B26-B27-B28 | C29: =C26-C27-C28 | D29: =D26-D27-D28

Sheet Weekly Summary
A1: metric | B1: value
A2: Gross Revenue | B2: =SUM(Event_PnL!B11:Z11)
A3: Net Revenue | B3: =B2-B8
A4: Total Food and Bev Cost | B4: =SUM((Event_PnL!B18:Z18):(Event_PnL!B19:Z19))
A5: Total Food and Bev Cost % | B5: =B4/B3
A6: Total Labor Cost | B6: =SUM(Event_PnL!B17:Z17)
A7: Total Labor Cost % | B7: =B6/B3
A8: Total Sales Tax | B8: =SUM(Event_PnL!B10:Z10)
A9: Opertaing Cost | B9: =SUM(B4,B6)
A10: Total Operating Profit | B10: =SUM(Event_PnL!B23:Z23)
A11: Operating Cost % | B11: =B9/B3
A12: Profit Margin % | B12: =(B10/B3)

Sheet Labor
A1: event_date | B1: event_name | C1: event_labor_cost | E1: weekly_labor_cost
E2: =SUM(C2:C100)

Sheet Invoices
A1: invoice_date | B1: vendor | C1: invoice_number | D1: category | E1: cost | F1: notes | G1: total_cost
A2: 03-07-202 | B2: All Natural Products Davidovich Bakery | C2: 948010 | D2: Bagels | E2: 32.99 | F2: 1 DZ, 4 types of Bagels | G2: =SUM(E2:E10)
A3: 03-05-2026 | B3: Chef's Warehouse | C3: 4908189 | D3: Eggs / Frozen Goods | E3: 288.56
A4: 03-05-2026 | B4: Baldor | C4: IV101-0028189541 | D4: Produce | E4: 786.1
A5: 03-07-2026 | B5: Baldor | C5: IV101-0028210021 | D5: Produce | E5: 244.01
A6: 03-06-2026 | B6: Prime Food Distributor | C6: 299306 | D6: Beef | E6: 1759.95 | F6: 4x Beef, Ribeye Boneless Prime
A7: 03-09-2026 | B7: Tivoli Mushrooms, LLC | C7: 35268 | D7: Mushrooms | E7: 371 | F7: +30lbs Mixed Mushrooms
A8: 03-06-2026 | B8: Liepper & Sons | C8: 111235 | D8: Fish | E8: 527.35 | F8: 53 ea; 800/1000 Branzino Fillet
A9: 03-06-2026 | B9: Liepper & Sons | C9: 111235 | D9: Fish | E9: 412.6 | F9: 7x sides Steelhead Salmon, skin-off
A10: 03-07-2026 | B10: Pain d Avignon | D10: Pastries | E10: 73.44 | F10: 1 DZ ea Croissant, Pain au Chocolat, Kouign Amann
A11: 03-07-2026 | B11: Eli's Bread | D11: Bread | E11: 60 | F11: 3 DZ mini Brioche hot dog, 4x 1.5# SF-style Sourdough, 1x, 5x5 Brioche Pullman
A12: 03-07-2026 | B12: Pat La Frieda | D12: Meat | E12: 143.7 | F12: 1 cs Chicken French Airline Cutlet
A13: 03-07-2026 | B13: Pat La Frieda | D13: Meat | E13: 134.4 | F13: 20lbs 2oz Dry Aged Beer Hamburger

Sheet Charts
